pyl402/__init__.py
pyl402/client/__init__.py
pyl402/client/l402.py
pyl402/token_store/__init__.py
pyl402/token_store/token_store.py
pyl402/wallet/__init__.py
pyl402/wallet/alby.py
pyl402/wallet/wallet.py
pyl402-0.1.2.dist-info/LICENSE
pyl402-0.1.2.dist-info/METADATA
pyl402-0.1.2.dist-info/WHEEL
pyl402-0.1.2.dist-info/RECORD
