Metadata-Version: 2.1
Name: pyl402
Version: 0.1.2
Summary: Python tools for the L402 protocol.
License: MIT
Author: Samuel Alarco
Author-email: samuel.alarco@sulusolutions.com
Requires-Python: >=3.10,<4.0
Classifier: License :: OSI Approved :: MIT License
Classifier: Programming Language :: Python :: 3
Classifier: Programming Language :: Python :: 3.10
Classifier: Programming Language :: Python :: 3.11
Classifier: Programming Language :: Python :: 3.12
Requires-Dist: httpx (>=0.27.0,<0.28.0)
